{
  "$schema": "../node_modules/@tauri-apps/cli/config.schema.json",
  "productName": "Sparktype",
  "version": "0.1.0",
  "identifier": "com.tauri.dev",
  "build": {
    "frontendDist": "../dist",
    "devUrl": "http://localhost:5174",
    "beforeDevCommand": "npm run dev:tauri",
    "beforeBuildCommand": "npm run build"
  },
  "app": {
    "windows": [
      {
        "title": "Sparktype",
        "width": 1200,
        "height": 800,
        "resizable": true,
        "fullscreen": false,
        "transparent": true,
        "decorations": true,
        "shadow": true,
        "label": "main",
        "titleBarStyle": "Overlay",
        "hiddenTitle": true,
        "trafficLightPosition": {
          "x": 15.0,
          "y": 20.0
        }
      }
    ],
    "security": {
      "csp": {
        "default-src": "'self' asset:",
        "img-src": "'self' asset: http://asset.localhost blob: data:",
        "script-src": "'self' 'unsafe-inline'",
        "style-src": "'self' 'unsafe-inline'"
      }
    },
    "withGlobalTauri": true
  },
  "bundle": {
    "active": true,
    "targets": "all",
    "icon": [
      "icons/32x32.png",
      "icons/128x128.png",
      "icons/128x128@2x.png",
      "icons/icon.icns",
      "icons/icon.ico"
    ]
  }
}
